---
title: 字节码技术
description: 了解 JVM 字节码技术的基础知识，包括字节码的概念、生成过程、实际应用场景以及如何通过字节码优化程序性能。
---

## 什么是字节码？

字节码（Bytecode）是一种中间代码，它是 Java 源代码编译后的产物。Java 编译器（`javac`）将 `.java` 文件编译为 `.class` 文件，这些 `.class` 文件包含的就是字节码。字节码是 JVM（Java 虚拟机）能够理解和执行的指令集。

字节码是平台无关的，这意味着它可以在任何安装了 JVM 的平台上运行。JVM 负责将字节码转换为特定平台的机器码，从而实现“一次编写，到处运行”的目标。

## 字节码的生成过程

Java 源代码通过 `javac` 编译器编译为字节码的过程可以分为以下几个步骤：

1. **词法分析**：将源代码分解为一个个的标记（tokens），如关键字、标识符、运算符等。
2. **语法分析**：根据语法规则将标记组织成语法树（Abstract Syntax Tree, AST）。
3. **语义分析**：检查语法树是否符合语义规则，例如类型检查、变量声明等。
4. **生成字节码**：将语法树转换为字节码，并生成 `.class` 文件。

以下是一个简单的 Java 代码示例及其对应的字节码：

```java
// HelloWorld.java
public class HelloWorld {
    public static void main(String[] args) {
        System.out.println("Hello, World!");
    }
}
```

使用 `javac` 编译后，生成的 `.class` 文件可以通过 `javap` 工具查看字节码：

```bash
javap -c HelloWorld
```

输出如下：

```plaintext
Compiled from "HelloWorld.java"
public class HelloWorld {
  public HelloWorld();
    Code:
       0: aload_0
       1: invokespecial #1                  // Method java/lang/Object."<init>":()V
       4: return

  public static void main(java.lang.String[]);
    Code:
       0: getstatic     #2                  // Field java/lang/System.out:Ljava/io/PrintStream;
       3: ldc           #3                  // String Hello, World!
       5: invokevirtual #4                  // Method java/io/PrintStream.println:(Ljava/lang/String;)V
       8: return
}
```

:::note
`javap` 是 JDK 自带的反编译工具，可以用来查看 `.class` 文件中的字节码。
:::

## 字节码的组成

字节码由一系列指令组成，每条指令都是一个字节（因此称为“字节码”）。这些指令可以分为以下几类：

- **加载和存储指令**：用于将数据从局部变量表加载到操作数栈，或者将数据从操作数栈存储到局部变量表。例如 `aload_0`、`istore_1` 等。
- **算术和逻辑指令**：用于执行算术和逻辑运算。例如 `iadd`、`isub`、`imul` 等。
- **控制转移指令**：用于控制程序的执行流程。例如 `ifeq`、`goto` 等。
- **方法调用和返回指令**：用于调用方法和从方法返回。例如 `invokevirtual`、`return` 等。
- **对象操作指令**：用于创建和操作对象。例如 `new`、`getfield` 等。

## 字节码的实际应用场景

### 1. 性能优化

通过分析字节码，开发者可以了解程序的执行细节，从而进行性能优化。例如，减少不必要的对象创建、优化循环结构等。

### 2. 动态代码生成

在某些场景下，程序需要在运行时动态生成字节码。例如，一些框架（如 Spring、Hibernate）会通过字节码增强技术（如 ASM、CGLIB）来生成代理类。

### 3. 反编译和代码保护

字节码可以被反编译为 Java 源代码，因此开发者需要采取措施保护代码不被轻易反编译。常见的保护措施包括混淆（Obfuscation）和加密。

## 字节码优化案例

假设我们有以下代码：

```java
public class Sum {
    public static int sum(int a, int b) {
        return a + b;
    }
}
```

编译后的字节码如下：

```plaintext
public static int sum(int, int);
    Code:
       0: iload_0
       1: iload_1
       2: iadd
       3: ireturn
```

通过分析字节码，我们可以看到 `sum` 方法的执行过程非常简单：加载两个参数到操作数栈，执行加法操作，然后返回结果。如果我们需要进一步优化，可以考虑内联（Inlining）等方法。

## 总结

字节码是 Java 程序运行的基础，理解字节码有助于我们更好地理解 Java 程序的执行过程，并进行性能优化。通过工具如 `javap`，我们可以查看和分析字节码，从而深入了解程序的内部机制。

## 附加资源

- [Oracle 官方文档：Java 字节码指令集](https://docs.oracle.com/javase/specs/jvms/se16/html/jvms-6.html)
- [ASM 字节码操作框架](https://asm.ow2.io/)
- [JVM 字节码指令详解](https://blog.csdn.net/qq_33589510/article/details/105160020)

## 练习

1. 编写一个简单的 Java 程序，使用 `javap` 查看其字节码，并尝试理解每条指令的含义。
2. 尝试使用 ASM 框架动态生成一个简单的类，并查看生成的字节码。